{
  "last_reset": "2026-01-07T17:32:23.032919",
  "corsair_vergeance": {
    "amazon": {
      "in_stock": false,
      "prices": []
    },
    "overclockers": {
      "in_stock": false,
      "prices": []
    },
    "newegg": {
      "in_stock": false,
      "prices": []
    },
    "paradigit": {
      "in_stock": true,
      "prices": [
        {
          "price": 350.99,
          "date": "2026-01-06 17:50"
        },
        {
          "price": 350.99,
          "date": "2026-01-06 18:41"
        },
        {
          "price": 350.99,
          "date": "2026-01-06 19:23"
        },
        {
          "price": 350.99,
          "date": "2026-01-06 19:42"
        },
        {
          "price": 350.99,
          "date": "2026-01-06 20:31"
        },
        {
          "price": 350.99,
          "date": "2026-01-06 21:27"
        },
        {
          "price": 350.99,
          "date": "2026-01-06 21:46"
        },
        {
          "price": 350.99,
          "date": "2026-01-06 22:29"
        },
        {
          "price": 350.99,
          "date": "2026-01-06 22:50"
        },
        {
          "price": 350.99,
          "date": "2026-01-06 23:27"
        },
        {
          "price": 350.99,
          "date": "2026-01-06 23:44"
        },
        {
          "price": 350.99,
          "date": "2026-01-07 02:12"
        },
        {
          "price": 350.99,
          "date": "2026-01-07 03:51"
        },
        {
          "price": 350.99,
          "date": "2026-01-07 04:47"
        },
        {
          "price": 350.99,
          "date": "2026-01-07 05:32"
        },
        {
          "price": 350.99,
          "date": "2026-01-07 06:44"
        },
        {
          "price": 350.99,
          "date": "2026-01-07 07:32"
        },
        {
          "price": 350.99,
          "date": "2026-01-07 08:40"
        },
        {
          "price": 350.99,
          "date": "2026-01-07 09:35"
        },
        {
          "price": 350.99,
          "date": "2026-01-07 10:32"
        },
        {
          "price": 350.99,
          "date": "2026-01-07 11:26"
        },
        {
          "price": 350.99,
          "date": "2026-01-07 11:45"
        },
        {
          "price": 350.99,
          "date": "2026-01-07 13:00"
        },
        {
          "price": 350.99,
          "date": "2026-01-07 13:57"
        },
        {
          "price": 374.99,
          "date": "2026-01-07 14:34"
        },
        {
          "price": 374.99,
          "date": "2026-01-07 15:33"
        },
        {
          "price": 374.99,
          "date": "2026-01-07 16:39"
        },
        {
          "price": 374.99,
          "date": "2026-01-07 17:32"
        },
        {
          "price": 374.99,
          "date": "2026-01-07 18:42"
        },
        {
          "price": 374.99,
          "date": "2026-01-07 19:26"
        },
        {
          "price": 374.99,
          "date": "2026-01-07 19:44"
        },
        {
          "price": 374.99,
          "date": "2026-01-07 20:33"
        },
        {
          "price": 374.99,
          "date": "2026-01-07 21:27"
        },
        {
          "price": 374.99,
          "date": "2026-01-07 21:46"
        },
        {
          "price": 374.99,
          "date": "2026-01-07 22:28"
        },
        {
          "price": 374.99,
          "date": "2026-01-07 22:48"
        },
        {
          "price": 374.99,
          "date": "2026-01-07 23:28"
        },
        {
          "price": 374.99,
          "date": "2026-01-07 23:45"
        },
        {
          "price": 374.99,
          "date": "2026-01-08 02:12"
        },
        {
          "price": 374.99,
          "date": "2026-01-08 03:51"
        },
        {
          "price": 374.99,
          "date": "2026-01-08 04:44"
        },
        {
          "price": 374.99,
          "date": "2026-01-08 05:32"
        },
        {
          "price": 374.99,
          "date": "2026-01-08 06:44"
        }
      ]
    }
  },
  "motherboard": {
    "amazon": {
      "in_stock": true,
      "prices": []
    },
    "overclockers": {
      "in_stock": false,
      "prices": []
    },
    "newegg": {
      "in_stock": false,
      "prices": []
    },
    "paradigit": {
      "in_stock": true,
      "prices": []
    }
  }
}