{
  "last_reset": "2026-01-05T17:29:02.763473",
  "corsair_vergeance": {
    "amazon": {
      "in_stock": false,
      "prices": []
    },
    "overclockers": {
      "in_stock": false,
      "prices": []
    },
    "newegg": {
      "in_stock": false,
      "prices": []
    },
    "paradigit": {
      "in_stock": true,
      "prices": [
        {
          "price": 421.99,
          "date": "2026-01-04 17:43"
        },
        {
          "price": 421.99,
          "date": "2026-01-04 18:37"
        },
        {
          "price": 421.99,
          "date": "2026-01-04 19:21"
        },
        {
          "price": 421.99,
          "date": "2026-01-04 19:40"
        },
        {
          "price": 421.99,
          "date": "2026-01-04 20:30"
        },
        {
          "price": 421.99,
          "date": "2026-01-04 21:25"
        },
        {
          "price": 421.99,
          "date": "2026-01-04 21:42"
        },
        {
          "price": 421.99,
          "date": "2026-01-04 22:26"
        },
        {
          "price": 421.99,
          "date": "2026-01-04 22:46"
        },
        {
          "price": 421.99,
          "date": "2026-01-04 23:26"
        },
        {
          "price": 421.99,
          "date": "2026-01-04 23:44"
        },
        {
          "price": 421.99,
          "date": "2026-01-05 02:28"
        },
        {
          "price": 421.99,
          "date": "2026-01-05 04:08"
        },
        {
          "price": 421.99,
          "date": "2026-01-05 05:10"
        },
        {
          "price": 421.99,
          "date": "2026-01-05 05:58"
        },
        {
          "price": 421.99,
          "date": "2026-01-05 06:53"
        },
        {
          "price": 421.99,
          "date": "2026-01-05 07:35"
        },
        {
          "price": 421.99,
          "date": "2026-01-05 08:43"
        },
        {
          "price": 421.99,
          "date": "2026-01-05 09:40"
        },
        {
          "price": 421.99,
          "date": "2026-01-05 10:33"
        },
        {
          "price": 421.99,
          "date": "2026-01-05 11:26"
        },
        {
          "price": 421.99,
          "date": "2026-01-05 11:44"
        },
        {
          "price": 421.99,
          "date": "2026-01-05 13:01"
        },
        {
          "price": 350.99,
          "date": "2026-01-05 13:57"
        },
        {
          "price": 350.99,
          "date": "2026-01-05 14:35"
        },
        {
          "price": 350.99,
          "date": "2026-01-05 15:32"
        },
        {
          "price": 350.99,
          "date": "2026-01-05 16:35"
        },
        {
          "price": 350.99,
          "date": "2026-01-05 17:29"
        },
        {
          "price": 350.99,
          "date": "2026-01-05 17:50"
        },
        {
          "price": 350.99,
          "date": "2026-01-05 18:42"
        },
        {
          "price": 350.99,
          "date": "2026-01-05 19:26"
        },
        {
          "price": 350.99,
          "date": "2026-01-05 19:43"
        },
        {
          "price": 350.99,
          "date": "2026-01-05 20:33"
        },
        {
          "price": 350.99,
          "date": "2026-01-05 21:28"
        }
      ]
    }
  },
  "motherboard": {
    "amazon": {
      "in_stock": true,
      "prices": []
    },
    "overclockers": {
      "in_stock": false,
      "prices": []
    },
    "newegg": {
      "in_stock": false,
      "prices": []
    },
    "paradigit": {
      "in_stock": true,
      "prices": []
    }
  }
}